[
    {
        "_id":"1",
        "author" : "ab",
        "subject": "computer science",
        "date" : "2023-03-25",
        "classCode" : "CSE341",
        "text" : "texthello world!hello world!hello world!hello world!texthello world!hello world!hello world!hello world!texthello world!hello world!hello world!hello world!texthello world!hello world!hello world!hello world!texthello world!hello world!hello world!hello world!texthello world!hello world!hello world!hello world!texthello world!hello world!hello world!hello world!texthello world!hello world!hello world!hello world!texthello world!hello world!hello world!hello world!texthello world!hello world!hello world!hello world!texthello world!hello world!hello world!hello world!texthello world!hello world!hello world!hello world!texthello world!hello world!hello world!hello world!texthello world!hello world!hello world!hello world!texthello world!hello world!hello world!hello world!texthello world!hello world!hello world!hello world!texthello world!hello world!hello world!hello world!texthello world!hello world!hello world!hello world!",
        "reply" : "10",
        "likes" : "4",
        "comment": 1
    },
    {
        "_id":"2",
        "subject": "computer science",
        "classCode" : "CSE341",
        "author" : "abc",
        "date" : "2023-03-25",
        "text" : "hello world!hello world!hello world!hello world!",
        "reply" : "10",
        "likes" : "4",
        "comment": 2
    },
    {
        "_id":"3",
        "author" : "abdd",
        "subject": "computer science",
        "date" : "2023-03-25",
        "classCode" : "CSE341",
        "text" : "hello world!hello world!hello world!hello world!",
        "reply" : "10",
        "likes" : "4",
        "comment": 3
    },
    {
        "_id":"4",
        "author" : "abcd",
        "subject": "computer science",
        "date" : "2023-03-25",
        "classCode" : "CSE341",
        "text" : "hello world!hello world!hello world!hello world!",
        "reply" : "10",
        "likes" : "4",
        "comment": 4
    }
]
